{
"type": "FeatureCollection",
"name": "boston_airport_geoJSON_4326",
"crs": { "type": "name", "properties": { "name": "urn:ogc:def:crs:OGC:1.3:CRS84" } },
"features": [
{ "type": "Feature", "properties": { "id": 1, "type": "Boston Logan Airport" }, "geometry": { "type": "Point", "coordinates": [ -71.019148128456152, 42.366122967264658 ] } }
]
}
